tests/conftest.py
tests/test.mp4
tests/test_cli.py
tests/test_cli_parity.py
tests/test_consistency.py
tests/test_model.py
tests/test_transnetv2_pytorch.py
tests/test_utils.py
transnetv2_pytorch/__init__.py
transnetv2_pytorch/__main__.py
transnetv2_pytorch/cli.py
transnetv2_pytorch/transnetv2-pytorch-weights.pth
transnetv2_pytorch/transnetv2_pytorch.py
transnetv2_pytorch-1.0.4.dist-info/licenses/LICENSE
transnetv2_pytorch-1.0.4.dist-info/METADATA
transnetv2_pytorch-1.0.4.dist-info/WHEEL
transnetv2_pytorch-1.0.4.dist-info/entry_points.txt
transnetv2_pytorch-1.0.4.dist-info/top_level.txt
transnetv2_pytorch-1.0.4.dist-info/RECORD
