Metadata-Version: 2.4
Name: transnetv2-pytorch
Version: 1.0.4
Summary: TransNetV2 PyTorch implementation for video scene detection
Author: TransNetV2 Contributors
License-Expression: MIT
Project-URL: Homepage, https://github.com/allenday/transnetv2_pytorch
Project-URL: Repository, https://github.com/allenday/transnetv2_pytorch
Project-URL: Issues, https://github.com/allenday/transnetv2_pytorch/issues
Classifier: Development Status :: 4 - Beta
Classifier: Intended Audience :: Developers
Classifier: Intended Audience :: Science/Research
Classifier: Operating System :: OS Independent
Classifier: Programming Language :: Python :: 3
Classifier: Programming Language :: Python :: 3.8
Classifier: Programming Language :: Python :: 3.9
Classifier: Programming Language :: Python :: 3.10
Classifier: Programming Language :: Python :: 3.11
Classifier: Topic :: Scientific/Engineering :: Artificial Intelligence
Classifier: Topic :: Multimedia :: Video
Requires-Python: >=3.10
License-File: LICENSE
Requires-Dist: ffmpeg-python
Requires-Dist: numpy
Requires-Dist: pandas
Requires-Dist: pillow
Requires-Dist: torch>=1.9.0
Requires-Dist: tqdm
Provides-Extra: dev
Requires-Dist: pytest; extra == "dev"
Requires-Dist: pytest-cov; extra == "dev"
Requires-Dist: black; extra == "dev"
Requires-Dist: flake8; extra == "dev"
Requires-Dist: mypy; extra == "dev"
Dynamic: license-file
